{
  "deployment_id": "deploy-1756433507",
  "timestamp": "2025-08-28T19:11:47.361103",
  "environment": "dev",
  "region": "us-west-1",
  "git_commit": "97dd020",
  "functions": {
    "agentic-file-analyzer-dev": {
      "version": "2",
      "code_sha256": "Z9vrIt7KKh+ZQjI0DVbdJXoreADKqtTumBPZBxotmFs=",
      "last_modified": "2025-08-29T02:11:36.000+0000",
      "aliases": {
        "LIVE": "2"
      }
    },
    "agentic-interview-processing-dev": {
      "version": "2",
      "code_sha256": "e5Fb+SNay6A4Jj0z6+fCmd6SKggTdNX64BeCHSt2urA=",
      "last_modified": "2025-08-29T02:11:38.000+0000",
      "aliases": {
        "LIVE": "2"
      }
    },
    "agentic-needs-analysis-dev": {
      "version": "2",
      "code_sha256": "l6LhtSF9Z6d53B/3DxNQjA3UuDVxh9jhLjoPSg98ZiI=",
      "last_modified": "2025-08-29T02:11:41.000+0000",
      "aliases": {
        "LIVE": "2"
      }
    },
    "agentic-hypergraph-builder-dev": {
      "version": "2",
      "code_sha256": "Dn0SM7tCd9hTe9CFlrj+4RYgwXbeUWFwQBsm9zGKL9I=",
      "last_modified": "2025-08-29T02:11:44.000+0000",
      "aliases": {
        "LIVE": "2"
      }
    }
  },
  "step_functions": {
    "state_machine_arn": "arn:aws:states:us-west-1:765455500375:stateMachine:agentic-framework-processing-workflow-dev",
    "update_date": "2025-08-28 19:08:37.577000-07:00"
  }
}